{"inputs":{"app/entry.server.tsx":{"bytes":2670,"imports":[{"path":"node:stream","kind":"import-statement","external":true},{"path":"@remix-run/node","kind":"import-statement","external":true},{"path":"@remix-run/react","kind":"import-statement","external":true},{"path":"isbot","kind":"import-statement","external":true},{"path":"react-dom/server","kind":"import-statement","external":true},{"path":"react/jsx-dev-runtime","kind":"import-statement","external":true}],"format":"esm"},"app/globals.css":{"bytes":55719,"imports":[]},"app/root.tsx":{"bytes":842,"imports":[{"path":"app/globals.css","kind":"import-statement","original":"./globals.css"},{"path":"@remix-run/react","kind":"import-statement","external":true},{"path":"react/jsx-dev-runtime","kind":"import-statement","external":true}],"format":"esm"},"app/components/Navbar.tsx":{"bytes":2016,"imports":[{"path":"@remix-run/react","kind":"import-statement","external":true},{"path":"react/jsx-dev-runtime","kind":"import-statement","external":true}],"format":"esm"},"app/utils/prisma.server.ts":{"bytes":406,"imports":[{"path":"@prisma/client","kind":"import-statement","external":true}],"format":"esm"},"app/utils/receitas.server.ts":{"bytes":46863,"imports":[{"path":"app/utils/prisma.server.ts","kind":"import-statement","original":"./prisma.server"}],"format":"esm"},"app/utils/despesas.server.ts":{"bytes":4156,"imports":[{"path":"app/utils/prisma.server.ts","kind":"import-statement","original":"./prisma.server"},{"path":"date-fns","kind":"import-statement","external":true},{"path":"date-fns/locale","kind":"import-statement","external":true}],"format":"esm"},"app/utils/icons.tsx":{"bytes":3933,"imports":[{"path":"react/jsx-dev-runtime","kind":"import-statement","external":true}],"format":"esm"},"app/utils/folha.server.ts":{"bytes":47102,"imports":[{"path":"app/utils/prisma.server.ts","kind":"import-statement","original":"./prisma.server"},{"path":"date-fns","kind":"import-statement","external":true},{"path":"date-fns/locale","kind":"import-statement","external":true},{"path":"lodash","kind":"import-statement","external":true}],"format":"esm"},"app/utils/auth.server.ts":{"bytes":42773,"imports":[{"path":"app/utils/prisma.server.ts","kind":"import-statement","original":"./prisma.server"},{"path":"@remix-run/node","kind":"import-statement","external":true},{"path":"bcryptjs","kind":"import-statement","external":true}],"format":"esm"},"app/routes/back_index_bak_25-07-2024.tsx":{"bytes":84620,"imports":[{"path":"app/components/Navbar.tsx","kind":"import-statement","original":"~/components/Navbar"},{"path":"@remix-run/node","kind":"import-statement","external":true},{"path":"app/utils/receitas.server.ts","kind":"import-statement","original":"~/utils/receitas.server"},{"path":"@remix-run/react","kind":"import-statement","external":true},{"path":"app/utils/despesas.server.ts","kind":"import-statement","original":"../utils/despesas.server"},{"path":"date-fns","kind":"import-statement","external":true},{"path":"date-fns/locale","kind":"import-statement","external":true},{"path":"app/utils/icons.tsx","kind":"import-statement","original":"~/utils/icons"},{"path":"app/utils/icons.tsx","kind":"import-statement","original":"../utils/icons"},{"path":"app/utils/folha.server.ts","kind":"import-statement","original":"~/utils/folha.server"},{"path":"lodash","kind":"import-statement","external":true},{"path":"chart.js","kind":"import-statement","external":true},{"path":"react-chartjs-2","kind":"import-statement","external":true},{"path":"app/utils/auth.server.ts","kind":"import-statement","original":"~/utils/auth.server"},{"path":"react/jsx-dev-runtime","kind":"import-statement","external":true}],"format":"esm"},"app/components/Modal.jsx":{"bytes":542,"imports":[{"path":"react/jsx-dev-runtime","kind":"import-statement","external":true}],"format":"esm"},"app/routes/folha.$funcionario.tsx":{"bytes":4391,"imports":[{"path":"@remix-run/node","kind":"import-statement","external":true},{"path":"@remix-run/node","kind":"import-statement","external":true},{"path":"@remix-run/react","kind":"import-statement","external":true},{"path":"~/components/Navbar","kind":"import-statement","external":true},{"path":"app/components/Modal.jsx","kind":"import-statement","original":"~/components/Modal"},{"path":"app/utils/folha.server.ts","kind":"import-statement","original":"~/utils/folha.server"},{"path":"react-icons/ri","kind":"import-statement","external":true},{"path":"react/jsx-dev-runtime","kind":"import-statement","external":true}],"format":"esm"},"app/routes/salario.$pagamento.tsx":{"bytes":5905,"imports":[{"path":"@remix-run/node","kind":"import-statement","external":true},{"path":"@remix-run/react","kind":"import-statement","external":true},{"path":"date-fns","kind":"import-statement","external":true},{"path":"date-fns/locale","kind":"import-statement","external":true},{"path":"react","kind":"import-statement","external":true},{"path":"lodash","kind":"import-statement","external":true},{"path":"app/components/Navbar.tsx","kind":"import-statement","original":"~/components/Navbar"},{"path":"app/utils/folha.server.ts","kind":"import-statement","original":"~/utils/folha.server"},{"path":"app/utils/icons.tsx","kind":"import-statement","original":"~/utils/icons"},{"path":"react/jsx-dev-runtime","kind":"import-statement","external":true}],"format":"esm"},"app/lib/utils.ts":{"bytes":166,"imports":[{"path":"clsx","kind":"import-statement","external":true},{"path":"tailwind-merge","kind":"import-statement","external":true}],"format":"esm"},"app/components/ui/dialog.tsx":{"bytes":3876,"imports":[{"path":"react","kind":"import-statement","external":true},{"path":"@radix-ui/react-dialog","kind":"import-statement","external":true},{"path":"@radix-ui/react-icons","kind":"import-statement","external":true},{"path":"app/lib/utils.ts","kind":"import-statement","original":"@/lib/utils"},{"path":"react/jsx-dev-runtime","kind":"import-statement","external":true}],"format":"esm"},"app/components/ui/command.tsx":{"bytes":4878,"imports":[{"path":"react","kind":"import-statement","external":true},{"path":"@radix-ui/react-dialog","kind":"import-statement","external":true},{"path":"@radix-ui/react-icons","kind":"import-statement","external":true},{"path":"cmdk","kind":"import-statement","external":true},{"path":"app/lib/utils.ts","kind":"import-statement","original":"@/lib/utils"},{"path":"app/components/ui/dialog.tsx","kind":"import-statement","original":"@/components/ui/dialog"},{"path":"react/jsx-dev-runtime","kind":"import-statement","external":true}],"format":"esm"},"app/components/ui/popover.tsx":{"bytes":1292,"imports":[{"path":"react","kind":"import-statement","external":true},{"path":"@radix-ui/react-popover","kind":"import-statement","external":true},{"path":"app/lib/utils.ts","kind":"import-statement","original":"@/lib/utils"},{"path":"react/jsx-dev-runtime","kind":"import-statement","external":true}],"format":"esm"},"app/components/ui/button.tsx":{"bytes":1836,"imports":[{"path":"react","kind":"import-statement","external":true},{"path":"@radix-ui/react-slot","kind":"import-statement","external":true},{"path":"class-variance-authority","kind":"import-statement","external":true},{"path":"app/lib/utils.ts","kind":"import-statement","original":"@/lib/utils"},{"path":"react/jsx-dev-runtime","kind":"import-statement","external":true}],"format":"esm"},"app/components/ui/input.tsx":{"bytes":801,"imports":[{"path":"react","kind":"import-statement","external":true},{"path":"app/lib/utils.ts","kind":"import-statement","original":"@/lib/utils"},{"path":"react/jsx-dev-runtime","kind":"import-statement","external":true}],"format":"esm"},"app/components/ui/separator.tsx":{"bytes":756,"imports":[{"path":"react","kind":"import-statement","external":true},{"path":"@radix-ui/react-separator","kind":"import-statement","external":true},{"path":"app/lib/utils.ts","kind":"import-statement","original":"@/lib/utils"},{"path":"react/jsx-dev-runtime","kind":"import-statement","external":true}],"format":"esm"},"app/routes/despesas.$despesa.tsx":{"bytes":7823,"imports":[{"path":"@remix-run/node","kind":"import-statement","external":true},{"path":"@remix-run/react","kind":"import-statement","external":true},{"path":"app/utils/despesas.server.ts","kind":"import-statement","original":"~/utils/despesas.server"},{"path":"app/components/ui/command.tsx","kind":"import-statement","original":"@/components/ui/command"},{"path":"app/components/ui/popover.tsx","kind":"import-statement","original":"@/components/ui/popover"},{"path":"app/components/ui/dialog.tsx","kind":"import-statement","original":"@/components/ui/dialog"},{"path":"app/components/Modal.jsx","kind":"import-statement","original":"~/components/Modal"},{"path":"react-icons/ri","kind":"import-statement","external":true},{"path":"app/components/ui/button.tsx","kind":"import-statement","original":"@/components/ui/button"},{"path":"lucide-react","kind":"import-statement","external":true},{"path":"react","kind":"import-statement","external":true},{"path":"app/lib/utils.ts","kind":"import-statement","original":"@/lib/utils"},{"path":"app/components/ui/input.tsx","kind":"import-statement","original":"@/components/ui/input"},{"path":"app/components/ui/separator.tsx","kind":"import-statement","original":"@/components/ui/separator"},{"path":"react/jsx-dev-runtime","kind":"import-statement","external":true}],"format":"esm"},"app/components/ui/label.tsx":{"bytes":724,"imports":[{"path":"react","kind":"import-statement","external":true},{"path":"@radix-ui/react-label","kind":"import-statement","external":true},{"path":"class-variance-authority","kind":"import-statement","external":true},{"path":"app/lib/utils.ts","kind":"import-statement","original":"@/lib/utils"},{"path":"react/jsx-dev-runtime","kind":"import-statement","external":true}],"format":"esm"},"app/components/ui/form.tsx":{"bytes":4097,"imports":[{"path":"react","kind":"import-statement","external":true},{"path":"@radix-ui/react-label","kind":"import-statement","external":true},{"path":"@radix-ui/react-slot","kind":"import-statement","external":true},{"path":"react-hook-form","kind":"import-statement","external":true},{"path":"app/lib/utils.ts","kind":"import-statement","original":"@/lib/utils"},{"path":"app/components/ui/label.tsx","kind":"import-statement","original":"@/components/ui/label"},{"path":"react/jsx-dev-runtime","kind":"import-statement","external":true}],"format":"esm"},"app/components/ui/calendar.tsx":{"bytes":3129,"imports":[{"path":"react","kind":"import-statement","external":true},{"path":"@radix-ui/react-icons","kind":"import-statement","external":true},{"path":"react-day-picker","kind":"import-statement","external":true},{"path":"date-fns/locale","kind":"import-statement","external":true},{"path":"app/lib/utils.ts","kind":"import-statement","original":"@/lib/utils"},{"path":"app/components/ui/button.tsx","kind":"import-statement","original":"@/components/ui/button"},{"path":"react/jsx-dev-runtime","kind":"import-statement","external":true}],"format":"esm"},"app/routes/receitas.$receita.tsx":{"bytes":49386,"imports":[{"path":"@remix-run/node","kind":"import-statement","external":true},{"path":"@remix-run/react","kind":"import-statement","external":true},{"path":"app/lib/utils.ts","kind":"import-statement","original":"@/lib/utils"},{"path":"app/utils/receitas.server.ts","kind":"import-statement","original":"~/utils/receitas.server"},{"path":"app/components/Modal.jsx","kind":"import-statement","original":"~/components/Modal"},{"path":"react-icons/ri","kind":"import-statement","external":true},{"path":"app/components/ui/dialog.tsx","kind":"import-statement","original":"@/components/ui/dialog"},{"path":"app/components/ui/separator.tsx","kind":"import-statement","original":"@/components/ui/separator"},{"path":"app/components/ui/button.tsx","kind":"import-statement","original":"@/components/ui/button"},{"path":"app/components/ui/form.tsx","kind":"import-statement","original":"@/components/ui/form"},{"path":"app/components/ui/label.tsx","kind":"import-statement","original":"@/components/ui/label"},{"path":"app/components/ui/popover.tsx","kind":"import-statement","original":"@/components/ui/popover"},{"path":"lucide-react","kind":"import-statement","external":true},{"path":"app/components/ui/command.tsx","kind":"import-statement","original":"@/components/ui/command"},{"path":"react","kind":"import-statement","external":true},{"path":"app/components/ui/calendar.tsx","kind":"import-statement","original":"@/components/ui/calendar"},{"path":"react/jsx-dev-runtime","kind":"import-statement","external":true}],"format":"esm"},"app/routes/receitas_antiga.tsx":{"bytes":6893,"imports":[{"path":"@remix-run/node","kind":"import-statement","external":true},{"path":"@remix-run/react","kind":"import-statement","external":true},{"path":"react","kind":"import-statement","external":true},{"path":"app/components/Navbar.tsx","kind":"import-statement","original":"~/components/Navbar"},{"path":"date-fns","kind":"import-statement","external":true},{"path":"lodash","kind":"import-statement","external":true},{"path":"app/utils/receitas.server.ts","kind":"import-statement","original":"~/utils/receitas.server"},{"path":"app/utils/auth.server.ts","kind":"import-statement","original":"~/utils/auth.server"},{"path":"react-icons/ri","kind":"import-statement","external":true},{"path":"react/jsx-dev-runtime","kind":"import-statement","external":true}],"format":"esm"},"app/components/ui/drawer.tsx":{"bytes":2930,"imports":[{"path":"react","kind":"import-statement","external":true},{"path":"vaul","kind":"import-statement","external":true},{"path":"app/lib/utils.ts","kind":"import-statement","original":"@/lib/utils"},{"path":"react/jsx-dev-runtime","kind":"import-statement","external":true}],"format":"esm"},"app/routes/despesas.new.tsx":{"bytes":7031,"imports":[{"path":"cleave.js/react","kind":"import-statement","external":true},{"path":"@remix-run/node","kind":"import-statement","external":true},{"path":"app/utils/despesas.server.ts","kind":"import-statement","original":"~/utils/despesas.server"},{"path":"@remix-run/react","kind":"import-statement","external":true},{"path":"app/components/Modal.jsx","kind":"import-statement","original":"~/components/Modal"},{"path":"app/components/ui/popover.tsx","kind":"import-statement","original":"@/components/ui/popover"},{"path":"react","kind":"import-statement","external":true},{"path":"app/components/ui/button.tsx","kind":"import-statement","original":"@/components/ui/button"},{"path":"lucide-react","kind":"import-statement","external":true},{"path":"app/components/ui/command.tsx","kind":"import-statement","original":"@/components/ui/command"},{"path":"app/components/ui/drawer.tsx","kind":"import-statement","original":"@/components/ui/drawer"},{"path":"app/lib/utils.ts","kind":"import-statement","original":"@/lib/utils"},{"path":"app/components/ui/input.tsx","kind":"import-statement","original":"@/components/ui/input"},{"path":"react/jsx-dev-runtime","kind":"import-statement","external":true}],"format":"esm"},"app/routes/estatisticas.tsx":{"bytes":65157,"imports":[{"path":"app/components/Navbar.tsx","kind":"import-statement","original":"~/components/Navbar"},{"path":"@remix-run/node","kind":"import-statement","external":true},{"path":"app/utils/receitas.server.ts","kind":"import-statement","original":"~/utils/receitas.server"},{"path":"@remix-run/react","kind":"import-statement","external":true},{"path":"app/utils/despesas.server.ts","kind":"import-statement","original":"../utils/despesas.server"},{"path":"date-fns","kind":"import-statement","external":true},{"path":"date-fns/locale","kind":"import-statement","external":true},{"path":"app/utils/icons.tsx","kind":"import-statement","original":"~/utils/icons"},{"path":"app/utils/icons.tsx","kind":"import-statement","original":"../utils/icons"},{"path":"app/utils/folha.server.ts","kind":"import-statement","original":"~/utils/folha.server"},{"path":"lodash","kind":"import-statement","external":true},{"path":"chart.js","kind":"import-statement","external":true},{"path":"react-chartjs-2","kind":"import-statement","external":true},{"path":"app/utils/auth.server.ts","kind":"import-statement","original":"~/utils/auth.server"},{"path":"react/jsx-dev-runtime","kind":"import-statement","external":true}],"format":"esm"},"app/routes/receitas.new.tsx":{"bytes":7244,"imports":[{"path":"cleave.js/react","kind":"import-statement","external":true},{"path":"@remix-run/node","kind":"import-statement","external":true},{"path":"app/utils/receitas.server.ts","kind":"import-statement","original":"~/utils/receitas.server"},{"path":"@remix-run/react","kind":"import-statement","external":true},{"path":"app/components/Modal.jsx","kind":"import-statement","original":"~/components/Modal"},{"path":"app/components/ui/calendar.tsx","kind":"import-statement","original":"@/components/ui/calendar"},{"path":"react","kind":"import-statement","external":true},{"path":"app/components/ui/form.tsx","kind":"import-statement","original":"@/components/ui/form"},{"path":"app/components/ui/label.tsx","kind":"import-statement","original":"@/components/ui/label"},{"path":"app/components/ui/popover.tsx","kind":"import-statement","original":"@/components/ui/popover"},{"path":"app/components/ui/button.tsx","kind":"import-statement","original":"@/components/ui/button"},{"path":"lucide-react","kind":"import-statement","external":true},{"path":"app/components/ui/command.tsx","kind":"import-statement","original":"@/components/ui/command"},{"path":"app/lib/utils.ts","kind":"import-statement","original":"@/lib/utils"},{"path":"react/jsx-dev-runtime","kind":"import-statement","external":true}],"format":"esm"},"app/routes/_index copy.tsx":{"bytes":167905,"imports":[{"path":"@remix-run/react","kind":"import-statement","external":true},{"path":"app/components/Navbar.tsx","kind":"import-statement","original":"~/components/Navbar"},{"path":"app/utils/receitas.server.ts","kind":"import-statement","original":"~/utils/receitas.server"},{"path":"lodash","kind":"import-statement","external":true},{"path":"app/utils/despesas.server.ts","kind":"import-statement","original":"~/utils/despesas.server"},{"path":"app/utils/folha.server.ts","kind":"import-statement","original":"~/utils/folha.server"},{"path":"react/jsx-dev-runtime","kind":"import-statement","external":true}],"format":"esm"},"app/routes/_index_bak.tsx":{"bytes":84668,"imports":[{"path":"app/components/Navbar.tsx","kind":"import-statement","original":"~/components/Navbar"},{"path":"@remix-run/node","kind":"import-statement","external":true},{"path":"app/utils/receitas.server.ts","kind":"import-statement","original":"~/utils/receitas.server"},{"path":"@remix-run/react","kind":"import-statement","external":true},{"path":"app/utils/despesas.server.ts","kind":"import-statement","original":"../utils/despesas.server"},{"path":"date-fns","kind":"import-statement","external":true},{"path":"date-fns/locale","kind":"import-statement","external":true},{"path":"app/utils/icons.tsx","kind":"import-statement","original":"~/utils/icons"},{"path":"app/utils/icons.tsx","kind":"import-statement","original":"../utils/icons"},{"path":"app/utils/folha.server.ts","kind":"import-statement","original":"~/utils/folha.server"},{"path":"lodash","kind":"import-statement","external":true},{"path":"chart.js","kind":"import-statement","external":true},{"path":"react-chartjs-2","kind":"import-statement","external":true},{"path":"app/utils/auth.server.ts","kind":"import-statement","original":"~/utils/auth.server"},{"path":"react/jsx-dev-runtime","kind":"import-statement","external":true}],"format":"esm"},"app/routes/folha.new.tsx":{"bytes":3358,"imports":[{"path":"@remix-run/node","kind":"import-statement","external":true},{"path":"@remix-run/react","kind":"import-statement","external":true},{"path":"~/components/Navbar","kind":"import-statement","external":true},{"path":"app/utils/folha.server.ts","kind":"import-statement","original":"~/utils/folha.server"},{"path":"app/components/Modal.jsx","kind":"import-statement","original":"~/components/Modal"},{"path":"react/jsx-dev-runtime","kind":"import-statement","external":true}],"format":"esm"},"app/components/ui/tabs.tsx":{"bytes":1877,"imports":[{"path":"react","kind":"import-statement","external":true},{"path":"@radix-ui/react-tabs","kind":"import-statement","external":true},{"path":"app/lib/utils.ts","kind":"import-statement","original":"@/lib/utils"},{"path":"react/jsx-dev-runtime","kind":"import-statement","external":true}],"format":"esm"},"app/components/ui/table.tsx":{"bytes":2859,"imports":[{"path":"react","kind":"import-statement","external":true},{"path":"app/lib/utils.ts","kind":"import-statement","original":"@/lib/utils"},{"path":"react/jsx-dev-runtime","kind":"import-statement","external":true}],"format":"esm"},"app/components/ui/accordion.tsx":{"bytes":1977,"imports":[{"path":"react","kind":"import-statement","external":true},{"path":"@radix-ui/react-accordion","kind":"import-statement","external":true},{"path":"@radix-ui/react-icons","kind":"import-statement","external":true},{"path":"app/lib/utils.ts","kind":"import-statement","original":"@/lib/utils"},{"path":"react/jsx-dev-runtime","kind":"import-statement","external":true}],"format":"esm"},"app/components/Fluxomes.tsx":{"bytes":58098,"imports":[{"path":"lodash","kind":"import-statement","external":true},{"path":"app/components/ui/table.tsx","kind":"import-statement","original":"@/components/ui/table"},{"path":"app/components/ui/accordion.tsx","kind":"import-statement","original":"@/components/ui/accordion"},{"path":"react/jsx-dev-runtime","kind":"import-statement","external":true}],"format":"esm"},"app/routes/cashflow.tsx":{"bytes":4319,"imports":[{"path":"app/components/Navbar.tsx","kind":"import-statement","original":"@/components/Navbar"},{"path":"app/components/ui/tabs.tsx","kind":"import-statement","original":"@/components/ui/tabs"},{"path":"date-fns","kind":"import-statement","external":true},{"path":"date-fns/locale/pt-BR","kind":"import-statement","external":true},{"path":"app/utils/receitas.server.ts","kind":"import-statement","original":"@/utils/receitas.server"},{"path":"app/utils/despesas.server.ts","kind":"import-statement","original":"@/utils/despesas.server"},{"path":"@remix-run/react","kind":"import-statement","external":true},{"path":"app/components/Fluxomes.tsx","kind":"import-statement","original":"@/components/Fluxomes"},{"path":"app/utils/folha.server.ts","kind":"import-statement","original":"~/utils/folha.server"},{"path":"react/jsx-dev-runtime","kind":"import-statement","external":true}],"format":"esm"},"app/routes/despesas.tsx":{"bytes":4468,"imports":[{"path":"@remix-run/node","kind":"import-statement","external":true},{"path":"@remix-run/react","kind":"import-statement","external":true},{"path":"app/components/Navbar.tsx","kind":"import-statement","original":"~/components/Navbar"},{"path":"app/utils/despesas.server.ts","kind":"import-statement","original":"~/utils/despesas.server"},{"path":"react","kind":"import-statement","external":true},{"path":"app/utils/auth.server.ts","kind":"import-statement","original":"~/utils/auth.server"},{"path":"date-fns","kind":"import-statement","external":true},{"path":"date-fns/locale","kind":"import-statement","external":true},{"path":"react/jsx-dev-runtime","kind":"import-statement","external":true}],"format":"esm"},"app/components/ui/select.tsx":{"bytes":5637,"imports":[{"path":"react","kind":"import-statement","external":true},{"path":"@radix-ui/react-icons","kind":"import-statement","external":true},{"path":"@radix-ui/react-select","kind":"import-statement","external":true},{"path":"app/lib/utils.ts","kind":"import-statement","original":"@/lib/utils"},{"path":"react/jsx-dev-runtime","kind":"import-statement","external":true}],"format":"esm"},"app/components/pagination.tsx":{"bytes":2983,"imports":[{"path":"@radix-ui/react-icons","kind":"import-statement","external":true},{"path":"app/components/ui/button.tsx","kind":"import-statement","original":"@/components/ui/button"},{"path":"app/components/ui/select.tsx","kind":"import-statement","original":"@/components/ui/select"},{"path":"react/jsx-dev-runtime","kind":"import-statement","external":true}],"format":"esm"},"app/components/Data-table.tsx":{"bytes":3677,"imports":[{"path":"@tanstack/react-table","kind":"import-statement","external":true},{"path":"app/components/ui/table.tsx","kind":"import-statement","original":"@/components/ui/table"},{"path":"react","kind":"import-statement","external":true},{"path":"app/components/ui/input.tsx","kind":"import-statement","original":"@/components/ui/input"},{"path":"app/components/pagination.tsx","kind":"import-statement","original":"./pagination"},{"path":"@remix-run/react","kind":"import-statement","external":true},{"path":"react/jsx-dev-runtime","kind":"import-statement","external":true}],"format":"esm"},"app/components/Reccolumns.tsx":{"bytes":3312,"imports":[{"path":"app/components/ui/button.tsx","kind":"import-statement","original":"@/components/ui/button"},{"path":"react-icons/fc","kind":"import-statement","external":true},{"path":"lucide-react","kind":"import-statement","external":true},{"path":"date-fns","kind":"import-statement","external":true},{"path":"date-fns/locale","kind":"import-statement","external":true},{"path":"@remix-run/react","kind":"import-statement","external":true},{"path":"app/components/ui/dialog.tsx","kind":"import-statement","original":"@/components/ui/dialog"},{"path":"@radix-ui/react-dropdown-menu","kind":"import-statement","external":true},{"path":"react/jsx-dev-runtime","kind":"import-statement","external":true}],"format":"esm"},"app/routes/receitas.tsx":{"bytes":41181,"imports":[{"path":"app/components/Data-table.tsx","kind":"import-statement","original":"@/components/Data-table"},{"path":"app/components/Navbar.tsx","kind":"import-statement","original":"@/components/Navbar"},{"path":"app/components/Reccolumns.tsx","kind":"import-statement","original":"@/components/Reccolumns"},{"path":"app/utils/auth.server.ts","kind":"import-statement","original":"@/utils/auth.server"},{"path":"app/utils/receitas.server.ts","kind":"import-statement","original":"@/utils/receitas.server"},{"path":"@remix-run/react","kind":"import-statement","external":true},{"path":"react/jsx-dev-runtime","kind":"import-statement","external":true}],"format":"esm"},"app/components/Resultados.tsx":{"bytes":8062,"imports":[{"path":"lodash","kind":"import-statement","external":true},{"path":"app/components/ui/table.tsx","kind":"import-statement","original":"@/components/ui/table"},{"path":"app/components/ui/accordion.tsx","kind":"import-statement","original":"@/components/ui/accordion"},{"path":"date-fns","kind":"import-statement","external":true},{"path":"date-fns/locale","kind":"import-statement","external":true},{"path":"react/jsx-dev-runtime","kind":"import-statement","external":true}],"format":"esm"},"app/components/ui/card.tsx":{"bytes":1847,"imports":[{"path":"react","kind":"import-statement","external":true},{"path":"app/lib/utils.ts","kind":"import-statement","original":"@/lib/utils"},{"path":"react/jsx-dev-runtime","kind":"import-statement","external":true}],"format":"esm"},"app/components/ui/badge.tsx":{"bytes":1199,"imports":[{"path":"react","kind":"import-statement","external":true},{"path":"class-variance-authority","kind":"import-statement","external":true},{"path":"app/lib/utils.ts","kind":"import-statement","original":"@/lib/utils"},{"path":"react/jsx-dev-runtime","kind":"import-statement","external":true}],"format":"esm"},"app/routes/_index.tsx":{"bytes":15482,"imports":[{"path":"app/components/Navbar.tsx","kind":"import-statement","original":"@/components/Navbar"},{"path":"app/components/Resultados.tsx","kind":"import-statement","original":"@/components/Resultados"},{"path":"app/utils/receitas.server.ts","kind":"import-statement","original":"@/utils/receitas.server"},{"path":"react-icons/io","kind":"import-statement","external":true},{"path":"date-fns","kind":"import-statement","external":true},{"path":"date-fns/locale","kind":"import-statement","external":true},{"path":"react","kind":"import-statement","external":true},{"path":"app/components/ui/card.tsx","kind":"import-statement","original":"@/components/ui/card"},{"path":"app/components/ui/badge.tsx","kind":"import-statement","original":"@/components/ui/badge"},{"path":"app/utils/auth.server.ts","kind":"import-statement","original":"@/utils/auth.server"},{"path":"@remix-run/react","kind":"import-statement","external":true},{"path":"lodash","kind":"import-statement","external":true},{"path":"app/utils/despesas.server.ts","kind":"import-statement","original":"@/utils/despesas.server"},{"path":"chart.js/auto","kind":"import-statement","external":true},{"path":"chart.js","kind":"import-statement","external":true},{"path":"react-chartjs-2","kind":"import-statement","external":true},{"path":"app/utils/folha.server.ts","kind":"import-statement","original":"@/utils/folha.server"},{"path":"react/jsx-dev-runtime","kind":"import-statement","external":true}],"format":"esm"},"app/routes/logout.ts":{"bytes":298,"imports":[{"path":"@remix-run/node","kind":"import-statement","external":true},{"path":"app/utils/auth.server.ts","kind":"import-statement","original":"~/utils/auth.server"}],"format":"esm"},"app/routes/fluxo.tsx":{"bytes":185521,"imports":[{"path":"@remix-run/react","kind":"import-statement","external":true},{"path":"app/components/Navbar.tsx","kind":"import-statement","original":"~/components/Navbar"},{"path":"app/utils/receitas.server.ts","kind":"import-statement","original":"~/utils/receitas.server"},{"path":"lodash","kind":"import-statement","external":true},{"path":"app/utils/despesas.server.ts","kind":"import-statement","original":"~/utils/despesas.server"},{"path":"app/utils/folha.server.ts","kind":"import-statement","original":"~/utils/folha.server"},{"path":"react/jsx-dev-runtime","kind":"import-statement","external":true}],"format":"esm"},"app/routes/folha.tsx":{"bytes":5861,"imports":[{"path":"@remix-run/node","kind":"import-statement","external":true},{"path":"@remix-run/react","kind":"import-statement","external":true},{"path":"react","kind":"import-statement","external":true},{"path":"app/components/Navbar.tsx","kind":"import-statement","original":"~/components/Navbar"},{"path":"app/utils/folha.server.ts","kind":"import-statement","original":"~/utils/folha.server"},{"path":"app/utils/icons.tsx","kind":"import-statement","original":"~/utils/icons"},{"path":"react-icons/fa","kind":"import-statement","external":true},{"path":"app/utils/auth.server.ts","kind":"import-statement","original":"~/utils/auth.server"},{"path":"react/jsx-dev-runtime","kind":"import-statement","external":true}],"format":"esm"},"app/components/auth/AuthForm.tsx":{"bytes":1867,"imports":[{"path":"@remix-run/react","kind":"import-statement","external":true},{"path":"react/jsx-dev-runtime","kind":"import-statement","external":true}],"format":"esm"},"app/routes/auth.tsx":{"bytes":41433,"imports":[{"path":"app/components/auth/AuthForm.tsx","kind":"import-statement","original":"~/components/auth/AuthForm"},{"path":"app/utils/auth.server.ts","kind":"import-statement","original":"~/utils/auth.server"},{"path":"@remix-run/react","kind":"import-statement","external":true},{"path":"react/jsx-dev-runtime","kind":"import-statement","external":true}],"format":"esm"},"app/routes/novo.tsx":{"bytes":1296,"imports":[{"path":"@remix-run/node","kind":"import-statement","external":true},{"path":"app/components/auth/AuthForm.tsx","kind":"import-statement","original":"~/components/auth/AuthForm"},{"path":"app/utils/auth.server.ts","kind":"import-statement","original":"~/utils/auth.server"},{"path":"react/jsx-dev-runtime","kind":"import-statement","external":true}],"format":"esm"},"server-assets-manifest:@remix-run/dev/assets-manifest":{"bytes":11135,"imports":[],"format":"esm"},"server-entry-module:@remix-run/dev/server-build":{"bytes":5912,"imports":[{"path":"app/entry.server.tsx","kind":"import-statement","original":"/Users/marciocarneiro/Documents/remix/admQuattor/app/entry.server.tsx"},{"path":"app/root.tsx","kind":"import-statement","original":"./root.tsx"},{"path":"app/routes/back_index_bak_25-07-2024.tsx","kind":"import-statement","original":"./routes/back_index_bak_25-07-2024.tsx"},{"path":"app/routes/folha.$funcionario.tsx","kind":"import-statement","original":"./routes/folha.$funcionario.tsx"},{"path":"app/routes/salario.$pagamento.tsx","kind":"import-statement","original":"./routes/salario.$pagamento.tsx"},{"path":"app/routes/despesas.$despesa.tsx","kind":"import-statement","original":"./routes/despesas.$despesa.tsx"},{"path":"app/routes/receitas.$receita.tsx","kind":"import-statement","original":"./routes/receitas.$receita.tsx"},{"path":"app/routes/receitas_antiga.tsx","kind":"import-statement","original":"./routes/receitas_antiga.tsx"},{"path":"app/routes/despesas.new.tsx","kind":"import-statement","original":"./routes/despesas.new.tsx"},{"path":"app/routes/estatisticas.tsx","kind":"import-statement","original":"./routes/estatisticas.tsx"},{"path":"app/routes/receitas.new.tsx","kind":"import-statement","original":"./routes/receitas.new.tsx"},{"path":"app/routes/_index copy.tsx","kind":"import-statement","original":"./routes/_index copy.tsx"},{"path":"app/routes/_index_bak.tsx","kind":"import-statement","original":"./routes/_index_bak.tsx"},{"path":"app/routes/folha.new.tsx","kind":"import-statement","original":"./routes/folha.new.tsx"},{"path":"app/routes/cashflow.tsx","kind":"import-statement","original":"./routes/cashflow.tsx"},{"path":"app/routes/despesas.tsx","kind":"import-statement","original":"./routes/despesas.tsx"},{"path":"app/routes/receitas.tsx","kind":"import-statement","original":"./routes/receitas.tsx"},{"path":"app/routes/_index.tsx","kind":"import-statement","original":"./routes/_index.tsx"},{"path":"app/routes/logout.ts","kind":"import-statement","original":"./routes/logout.ts"},{"path":"app/routes/fluxo.tsx","kind":"import-statement","original":"./routes/fluxo.tsx"},{"path":"app/routes/folha.tsx","kind":"import-statement","original":"./routes/folha.tsx"},{"path":"app/routes/auth.tsx","kind":"import-statement","original":"./routes/auth.tsx"},{"path":"app/routes/novo.tsx","kind":"import-statement","original":"./routes/novo.tsx"},{"path":"server-assets-manifest:@remix-run/dev/assets-manifest","kind":"import-statement","original":"@remix-run/dev/assets-manifest"}],"format":"esm"},"<stdin>":{"bytes":44,"imports":[{"path":"server-entry-module:@remix-run/dev/server-build","kind":"import-statement","original":"@remix-run/dev/server-build"}],"format":"esm"}},"outputs":{"api/_assets/globals-G66WPW5G.css":{"imports":[],"exports":[],"inputs":{"app/globals.css":{"bytesInOutput":55719}},"bytes":55719},"api/index.js.map":{"imports":[],"exports":[],"inputs":{},"bytes":1623400},"api/index.js":{"imports":[{"path":"node:stream","kind":"require-call","external":true},{"path":"@remix-run/react","kind":"require-call","external":true},{"path":"isbot","kind":"require-call","external":true},{"path":"react-dom/server","kind":"require-call","external":true},{"path":"react/jsx-dev-runtime","kind":"require-call","external":true},{"path":"api/_assets/globals-G66WPW5G.css","kind":"file-loader"},{"path":"@remix-run/react","kind":"require-call","external":true},{"path":"react/jsx-dev-runtime","kind":"require-call","external":true},{"path":"@remix-run/react","kind":"require-call","external":true},{"path":"react/jsx-dev-runtime","kind":"require-call","external":true},{"path":"@remix-run/node","kind":"require-call","external":true},{"path":"@prisma/client","kind":"require-call","external":true},{"path":"@remix-run/react","kind":"require-call","external":true},{"path":"date-fns","kind":"require-call","external":true},{"path":"date-fns/locale","kind":"require-call","external":true},{"path":"date-fns","kind":"require-call","external":true},{"path":"date-fns/locale","kind":"require-call","external":true},{"path":"react/jsx-dev-runtime","kind":"require-call","external":true},{"path":"date-fns","kind":"require-call","external":true},{"path":"date-fns/locale","kind":"require-call","external":true},{"path":"lodash","kind":"require-call","external":true},{"path":"lodash","kind":"require-call","external":true},{"path":"chart.js","kind":"require-call","external":true},{"path":"react-chartjs-2","kind":"require-call","external":true},{"path":"@remix-run/node","kind":"require-call","external":true},{"path":"bcryptjs","kind":"require-call","external":true},{"path":"react/jsx-dev-runtime","kind":"require-call","external":true},{"path":"@remix-run/node","kind":"require-call","external":true},{"path":"@remix-run/node","kind":"require-call","external":true},{"path":"@remix-run/react","kind":"require-call","external":true},{"path":"react/jsx-dev-runtime","kind":"require-call","external":true},{"path":"react-icons/ri","kind":"require-call","external":true},{"path":"react/jsx-dev-runtime","kind":"require-call","external":true},{"path":"@remix-run/node","kind":"require-call","external":true},{"path":"@remix-run/react","kind":"require-call","external":true},{"path":"date-fns","kind":"require-call","external":true},{"path":"date-fns/locale","kind":"require-call","external":true},{"path":"react","kind":"require-call","external":true},{"path":"lodash","kind":"require-call","external":true},{"path":"react/jsx-dev-runtime","kind":"require-call","external":true},{"path":"@remix-run/node","kind":"require-call","external":true},{"path":"@remix-run/react","kind":"require-call","external":true},{"path":"react","kind":"require-call","external":true},{"path":"@radix-ui/react-icons","kind":"require-call","external":true},{"path":"cmdk","kind":"require-call","external":true},{"path":"clsx","kind":"require-call","external":true},{"path":"tailwind-merge","kind":"require-call","external":true},{"path":"react","kind":"require-call","external":true},{"path":"@radix-ui/react-dialog","kind":"require-call","external":true},{"path":"@radix-ui/react-icons","kind":"require-call","external":true},{"path":"react/jsx-dev-runtime","kind":"require-call","external":true},{"path":"react/jsx-dev-runtime","kind":"require-call","external":true},{"path":"react","kind":"require-call","external":true},{"path":"@radix-ui/react-popover","kind":"require-call","external":true},{"path":"react/jsx-dev-runtime","kind":"require-call","external":true},{"path":"react-icons/ri","kind":"require-call","external":true},{"path":"react","kind":"require-call","external":true},{"path":"@radix-ui/react-slot","kind":"require-call","external":true},{"path":"class-variance-authority","kind":"require-call","external":true},{"path":"react/jsx-dev-runtime","kind":"require-call","external":true},{"path":"lucide-react","kind":"require-call","external":true},{"path":"react","kind":"require-call","external":true},{"path":"react","kind":"require-call","external":true},{"path":"react/jsx-dev-runtime","kind":"require-call","external":true},{"path":"react","kind":"require-call","external":true},{"path":"@radix-ui/react-separator","kind":"require-call","external":true},{"path":"react/jsx-dev-runtime","kind":"require-call","external":true},{"path":"react/jsx-dev-runtime","kind":"require-call","external":true},{"path":"@remix-run/node","kind":"require-call","external":true},{"path":"@remix-run/react","kind":"require-call","external":true},{"path":"react-icons/ri","kind":"require-call","external":true},{"path":"react","kind":"require-call","external":true},{"path":"@radix-ui/react-slot","kind":"require-call","external":true},{"path":"react-hook-form","kind":"require-call","external":true},{"path":"react","kind":"require-call","external":true},{"path":"@radix-ui/react-label","kind":"require-call","external":true},{"path":"class-variance-authority","kind":"require-call","external":true},{"path":"react/jsx-dev-runtime","kind":"require-call","external":true},{"path":"react/jsx-dev-runtime","kind":"require-call","external":true},{"path":"lucide-react","kind":"require-call","external":true},{"path":"react","kind":"require-call","external":true},{"path":"@radix-ui/react-icons","kind":"require-call","external":true},{"path":"react-day-picker","kind":"require-call","external":true},{"path":"date-fns/locale","kind":"require-call","external":true},{"path":"react/jsx-dev-runtime","kind":"require-call","external":true},{"path":"react/jsx-dev-runtime","kind":"require-call","external":true},{"path":"@remix-run/node","kind":"require-call","external":true},{"path":"@remix-run/react","kind":"require-call","external":true},{"path":"react","kind":"require-call","external":true},{"path":"date-fns","kind":"require-call","external":true},{"path":"lodash","kind":"require-call","external":true},{"path":"react-icons/ri","kind":"require-call","external":true},{"path":"react/jsx-dev-runtime","kind":"require-call","external":true},{"path":"cleave.js/react","kind":"require-call","external":true},{"path":"@remix-run/node","kind":"require-call","external":true},{"path":"@remix-run/react","kind":"require-call","external":true},{"path":"react","kind":"require-call","external":true},{"path":"lucide-react","kind":"require-call","external":true},{"path":"react","kind":"require-call","external":true},{"path":"vaul","kind":"require-call","external":true},{"path":"react/jsx-dev-runtime","kind":"require-call","external":true},{"path":"react/jsx-dev-runtime","kind":"require-call","external":true},{"path":"@remix-run/node","kind":"require-call","external":true},{"path":"@remix-run/react","kind":"require-call","external":true},{"path":"date-fns","kind":"require-call","external":true},{"path":"date-fns/locale","kind":"require-call","external":true},{"path":"lodash","kind":"require-call","external":true},{"path":"chart.js","kind":"require-call","external":true},{"path":"react-chartjs-2","kind":"require-call","external":true},{"path":"react/jsx-dev-runtime","kind":"require-call","external":true},{"path":"cleave.js/react","kind":"require-call","external":true},{"path":"@remix-run/node","kind":"require-call","external":true},{"path":"@remix-run/react","kind":"require-call","external":true},{"path":"react","kind":"require-call","external":true},{"path":"lucide-react","kind":"require-call","external":true},{"path":"react/jsx-dev-runtime","kind":"require-call","external":true},{"path":"@remix-run/react","kind":"require-call","external":true},{"path":"lodash","kind":"require-call","external":true},{"path":"react/jsx-dev-runtime","kind":"require-call","external":true},{"path":"@remix-run/node","kind":"require-call","external":true},{"path":"@remix-run/react","kind":"require-call","external":true},{"path":"date-fns","kind":"require-call","external":true},{"path":"date-fns/locale","kind":"require-call","external":true},{"path":"lodash","kind":"require-call","external":true},{"path":"chart.js","kind":"require-call","external":true},{"path":"react-chartjs-2","kind":"require-call","external":true},{"path":"react/jsx-dev-runtime","kind":"require-call","external":true},{"path":"@remix-run/node","kind":"require-call","external":true},{"path":"@remix-run/react","kind":"require-call","external":true},{"path":"react/jsx-dev-runtime","kind":"require-call","external":true},{"path":"react","kind":"require-call","external":true},{"path":"@radix-ui/react-tabs","kind":"require-call","external":true},{"path":"react/jsx-dev-runtime","kind":"require-call","external":true},{"path":"date-fns","kind":"require-call","external":true},{"path":"date-fns/locale/pt-BR","kind":"require-call","external":true},{"path":"@remix-run/react","kind":"require-call","external":true},{"path":"lodash","kind":"require-call","external":true},{"path":"react","kind":"require-call","external":true},{"path":"react/jsx-dev-runtime","kind":"require-call","external":true},{"path":"react","kind":"require-call","external":true},{"path":"@radix-ui/react-accordion","kind":"require-call","external":true},{"path":"@radix-ui/react-icons","kind":"require-call","external":true},{"path":"react/jsx-dev-runtime","kind":"require-call","external":true},{"path":"react/jsx-dev-runtime","kind":"require-call","external":true},{"path":"react/jsx-dev-runtime","kind":"require-call","external":true},{"path":"@remix-run/node","kind":"require-call","external":true},{"path":"@remix-run/react","kind":"require-call","external":true},{"path":"react","kind":"require-call","external":true},{"path":"date-fns","kind":"require-call","external":true},{"path":"date-fns/locale","kind":"require-call","external":true},{"path":"react/jsx-dev-runtime","kind":"require-call","external":true},{"path":"@tanstack/react-table","kind":"require-call","external":true},{"path":"react","kind":"require-call","external":true},{"path":"@radix-ui/react-icons","kind":"require-call","external":true},{"path":"react","kind":"require-call","external":true},{"path":"@radix-ui/react-icons","kind":"require-call","external":true},{"path":"@radix-ui/react-select","kind":"require-call","external":true},{"path":"react/jsx-dev-runtime","kind":"require-call","external":true},{"path":"react/jsx-dev-runtime","kind":"require-call","external":true},{"path":"@remix-run/react","kind":"require-call","external":true},{"path":"react/jsx-dev-runtime","kind":"require-call","external":true},{"path":"react-icons/fc","kind":"require-call","external":true},{"path":"lucide-react","kind":"require-call","external":true},{"path":"date-fns","kind":"require-call","external":true},{"path":"date-fns/locale","kind":"require-call","external":true},{"path":"@remix-run/react","kind":"require-call","external":true},{"path":"@radix-ui/react-dropdown-menu","kind":"require-call","external":true},{"path":"react/jsx-dev-runtime","kind":"require-call","external":true},{"path":"@remix-run/react","kind":"require-call","external":true},{"path":"react/jsx-dev-runtime","kind":"require-call","external":true},{"path":"lodash","kind":"require-call","external":true},{"path":"date-fns","kind":"require-call","external":true},{"path":"date-fns/locale","kind":"require-call","external":true},{"path":"react/jsx-dev-runtime","kind":"require-call","external":true},{"path":"react-icons/io","kind":"require-call","external":true},{"path":"date-fns","kind":"require-call","external":true},{"path":"date-fns/locale","kind":"require-call","external":true},{"path":"react","kind":"require-call","external":true},{"path":"react","kind":"require-call","external":true},{"path":"react/jsx-dev-runtime","kind":"require-call","external":true},{"path":"class-variance-authority","kind":"require-call","external":true},{"path":"react/jsx-dev-runtime","kind":"require-call","external":true},{"path":"@remix-run/react","kind":"require-call","external":true},{"path":"lodash","kind":"require-call","external":true},{"path":"chart.js/auto","kind":"require-call","external":true},{"path":"chart.js","kind":"require-call","external":true},{"path":"react-chartjs-2","kind":"require-call","external":true},{"path":"react/jsx-dev-runtime","kind":"require-call","external":true},{"path":"@remix-run/node","kind":"require-call","external":true},{"path":"@remix-run/react","kind":"require-call","external":true},{"path":"lodash","kind":"require-call","external":true},{"path":"react/jsx-dev-runtime","kind":"require-call","external":true},{"path":"@remix-run/node","kind":"require-call","external":true},{"path":"@remix-run/react","kind":"require-call","external":true},{"path":"react","kind":"require-call","external":true},{"path":"react-icons/fa","kind":"require-call","external":true},{"path":"react/jsx-dev-runtime","kind":"require-call","external":true},{"path":"@remix-run/react","kind":"require-call","external":true},{"path":"react/jsx-dev-runtime","kind":"require-call","external":true},{"path":"@remix-run/react","kind":"require-call","external":true},{"path":"react/jsx-dev-runtime","kind":"require-call","external":true},{"path":"react/jsx-dev-runtime","kind":"require-call","external":true}],"exports":[],"entryPoint":"<stdin>","inputs":{"<stdin>":{"bytesInOutput":294},"app/entry.server.tsx":{"bytesInOutput":2972},"app/root.tsx":{"bytesInOutput":2498},"app/globals.css":{"bytesInOutput":61},"app/routes/back_index_bak_25-07-2024.tsx":{"bytesInOutput":136236},"app/components/Navbar.tsx":{"bytesInOutput":4701},"app/utils/prisma.server.ts":{"bytesInOutput":166},"app/utils/receitas.server.ts":{"bytesInOutput":42744},"app/utils/despesas.server.ts":{"bytesInOutput":2712},"app/utils/icons.tsx":{"bytesInOutput":6986},"app/utils/folha.server.ts":{"bytesInOutput":44208},"app/utils/auth.server.ts":{"bytesInOutput":41561},"app/routes/folha.$funcionario.tsx":{"bytesInOutput":12534},"app/components/Modal.jsx":{"bytesInOutput":965},"app/routes/salario.$pagamento.tsx":{"bytesInOutput":18248},"app/routes/despesas.$despesa.tsx":{"bytesInOutput":20038},"app/components/ui/command.tsx":{"bytesInOutput":4807},"app/lib/utils.ts":{"bytesInOutput":189},"app/components/ui/dialog.tsx":{"bytesInOutput":5106},"app/components/ui/popover.tsx":{"bytesInOutput":1357},"app/components/ui/button.tsx":{"bytesInOutput":1803},"app/components/ui/input.tsx":{"bytesInOutput":846},"app/components/ui/separator.tsx":{"bytesInOutput":803},"app/routes/receitas.$receita.tsx":{"bytesInOutput":62290},"app/components/ui/form.tsx":{"bytesInOutput":3763},"app/components/ui/label.tsx":{"bytesInOutput":783},"app/components/ui/calendar.tsx":{"bytesInOutput":3729},"app/routes/receitas_antiga.tsx":{"bytesInOutput":17422},"app/routes/despesas.new.tsx":{"bytesInOutput":17750},"app/components/ui/drawer.tsx":{"bytesInOutput":3950},"app/routes/estatisticas.tsx":{"bytesInOutput":89619},"app/routes/receitas.new.tsx":{"bytesInOutput":15760},"app/routes/_index copy.tsx":{"bytesInOutput":274174},"app/routes/_index_bak.tsx":{"bytesInOutput":132745},"app/routes/folha.new.tsx":{"bytesInOutput":10172},"app/routes/cashflow.tsx":{"bytesInOutput":9155},"app/components/ui/tabs.tsx":{"bytesInOutput":2015},"app/components/Fluxomes.tsx":{"bytesInOutput":72100},"app/components/ui/table.tsx":{"bytesInOutput":3666},"app/components/ui/accordion.tsx":{"bytesInOutput":2594},"app/routes/despesas.tsx":{"bytesInOutput":11851},"app/routes/receitas.tsx":{"bytesInOutput":41260},"app/components/Data-table.tsx":{"bytesInOutput":6120},"app/components/pagination.tsx":{"bytesInOutput":8517},"app/components/ui/select.tsx":{"bytesInOutput":7767},"app/components/Reccolumns.tsx":{"bytesInOutput":8637},"app/routes/_index.tsx":{"bytesInOutput":27492},"app/components/Resultados.tsx":{"bytesInOutput":17575},"app/components/ui/card.tsx":{"bytesInOutput":2405},"app/components/ui/badge.tsx":{"bytesInOutput":1249},"app/routes/logout.ts":{"bytesInOutput":325},"app/routes/fluxo.tsx":{"bytesInOutput":391945},"app/routes/folha.tsx":{"bytesInOutput":13818},"app/routes/auth.tsx":{"bytesInOutput":41366},"app/components/auth/AuthForm.tsx":{"bytesInOutput":4239},"app/routes/novo.tsx":{"bytesInOutput":2119},"server-assets-manifest:@remix-run/dev/assets-manifest":{"bytesInOutput":10953},"server-entry-module:@remix-run/dev/server-build":{"bytesInOutput":4321}},"bytes":1679683}}}